bytedance_compatible_bloom_filter/__init__.py
bytedance_compatible_bloom_filter-0.0.1.dist-info/METADATA
bytedance_compatible_bloom_filter-0.0.1.dist-info/WHEEL
bytedance_compatible_bloom_filter-0.0.1.dist-info/top_level.txt
bytedance_compatible_bloom_filter-0.0.1.dist-info/RECORD
